{
  "date": "2026-04-04",
  "generated": "2026-04-04T19:14:36",
  "game_count": 3,
  "strong": 0,
  "games": [
    {
      "matchup": "WAS @ MIA",
      "home_abbr": "MIA",
      "away_abbr": "WAS",
      "home_pct": 63.2,
      "away_pct": 36.8,
      "pick": "Miami Heat",
      "winner_is": "home",
      "confidence": "lean",
      "home_out": [
        {
          "name": "Tyler Herro",
          "status": "Out",
          "star": true
        },
        {
          "name": "Norman Powell",
          "status": "Out",
          "star": false
        },
        {
          "name": "Terry Rozier",
          "status": "Out",
          "star": false
        }
      ],
      "away_out": [
        {
          "name": "Tristan Vukcevic",
          "status": "Out",
          "star": true
        },
        {
          "name": "Alex Sarr",
          "status": "Out",
          "star": false
        },
        {
          "name": "Trae Young",
          "status": "Out",
          "star": false
        },
        {
          "name": "Kyshawn George",
          "status": "Out",
          "star": false
        },
        {
          "name": "Anthony Davis",
          "status": "Out",
          "star": false
        },
        {
          "name": "D'Angelo Russell",
          "status": "Out",
          "star": false
        },
        {
          "name": "Cam Whitmore",
          "status": "Out",
          "star": false
        }
      ],
      "stats": [
        {
          "name": "Elo rating",
          "home": "1455",
          "away": "1487",
          "rawHome": 1455.2,
          "rawAway": 1486.7,
          "higherBetter": true
        },
        {
          "name": "Points / g",
          "home": "123.1",
          "away": "115.1",
          "rawHome": 123.1,
          "rawAway": 115.1,
          "higherBetter": true
        },
        {
          "name": "Rebounds / g",
          "home": "43.3",
          "away": "37.4",
          "rawHome": 43.3,
          "rawAway": 37.4,
          "higherBetter": true
        },
        {
          "name": "Assists / g",
          "home": "29.5",
          "away": "25.0",
          "rawHome": 29.5,
          "rawAway": 25.0,
          "higherBetter": true
        },
        {
          "name": "Turnovers / g",
          "home": "11.3",
          "away": "13.4",
          "rawHome": 11.3,
          "rawAway": 13.4,
          "higherBetter": false
        }
      ]
    },
    {
      "matchup": "SAS @ DEN",
      "home_abbr": "DEN",
      "away_abbr": "SAS",
      "home_pct": 47.8,
      "away_pct": 52.2,
      "pick": "San Antonio Spurs",
      "winner_is": "away",
      "confidence": "tossup",
      "home_out": [
        {
          "name": "Zeke Nnaji",
          "status": "Out",
          "star": true
        },
        {
          "name": "Spencer Jones",
          "status": "Out",
          "star": false
        },
        {
          "name": "Peyton Watson",
          "status": "Out",
          "star": false
        }
      ],
      "away_out": [
        {
          "name": "Emanuel Miller",
          "status": "Out",
          "star": true
        },
        {
          "name": "David Jones Garcia",
          "status": "Out",
          "star": false
        }
      ],
      "stats": [
        {
          "name": "Elo rating",
          "home": "1514",
          "away": "1493",
          "rawHome": 1513.7,
          "rawAway": 1493.5,
          "higherBetter": true
        },
        {
          "name": "Rebounds / g",
          "home": "46.2",
          "away": "50.4",
          "rawHome": 46.2,
          "rawAway": 50.4,
          "higherBetter": true
        },
        {
          "name": "Blocks / g",
          "home": "3.3",
          "away": "5.4",
          "rawHome": 3.3,
          "rawAway": 5.4,
          "higherBetter": true
        },
        {
          "name": "Steals / g",
          "home": "5.4",
          "away": "7.1",
          "rawHome": 5.4,
          "rawAway": 7.1,
          "higherBetter": true
        },
        {
          "name": "Points / g",
          "home": "127.5",
          "away": "126.1",
          "rawHome": 127.5,
          "rawAway": 126.1,
          "higherBetter": true
        }
      ]
    },
    {
      "matchup": "DET @ PHI",
      "home_abbr": "PHI",
      "away_abbr": "DET",
      "home_pct": 34.8,
      "away_pct": 65.2,
      "pick": "Detroit Pistons",
      "winner_is": "away",
      "confidence": "lean",
      "home_out": [
        {
          "name": "Joel Embiid",
          "status": "Out",
          "star": true
        },
        {
          "name": "Johni Broome",
          "status": "Out",
          "star": false
        }
      ],
      "away_out": [
        {
          "name": "Isaiah Stewart",
          "status": "Out",
          "star": true
        },
        {
          "name": "Cade Cunningham",
          "status": "Out",
          "star": false
        }
      ],
      "stats": [
        {
          "name": "Elo rating",
          "home": "1481",
          "away": "1480",
          "rawHome": 1480.7,
          "rawAway": 1480.5,
          "higherBetter": true
        },
        {
          "name": "Points / g",
          "home": "122.5",
          "away": "119.2",
          "rawHome": 122.5,
          "rawAway": 119.2,
          "higherBetter": true
        },
        {
          "name": "Assists / g",
          "home": "27.8",
          "away": "31.0",
          "rawHome": 27.8,
          "rawAway": 31.0,
          "higherBetter": true
        },
        {
          "name": "Turnovers / g",
          "home": "11.7",
          "away": "14.2",
          "rawHome": 11.7,
          "rawAway": 14.2,
          "higherBetter": false
        },
        {
          "name": "Steals / g",
          "home": "7.6",
          "away": "9.9",
          "rawHome": 7.6,
          "rawAway": 9.9,
          "higherBetter": true
        }
      ]
    }
  ]
}
